pyncm_async/__init__.py
pyncm_async/apis/__init__.py
pyncm_async/apis/album.py
pyncm_async/apis/artist.py
pyncm_async/apis/cloud.py
pyncm_async/apis/cloudsearch.py
pyncm_async/apis/exception.py
pyncm_async/apis/login.py
pyncm_async/apis/playlist.py
pyncm_async/apis/track.py
pyncm_async/apis/user.py
pyncm_async/apis/video.py
pyncm_async/apis/miniprograms/__init__.py
pyncm_async/apis/miniprograms/difm.py
pyncm_async/apis/miniprograms/radio.py
pyncm_async/apis/miniprograms/sportsfm.py
pyncm_async/apis/miniprograms/zonefm.py
pyncm_async/utils/__init__.py
pyncm_async/utils/aes.py
pyncm_async/utils/constant.py
pyncm_async/utils/crypto.py
pyncm_async/utils/security.py
pyncm_async-1.8.2.dist-info/licenses/LICENSE
pyncm_async-1.8.2.dist-info/METADATA
pyncm_async-1.8.2.dist-info/WHEEL
pyncm_async-1.8.2.dist-info/top_level.txt
pyncm_async-1.8.2.dist-info/RECORD
