Metadata-Version: 2.4
Name: pyncm-async
Version: 1.8.2
Summary: NeteaseCloudMusic APIs for Python 3.x 适用于 Python 3 的网易云音乐异步 API
Home-page: https://github.com/greats3an/pyncm/tree/async
Author: greats3an
Author-email: greats3an@gmail.com
Classifier: Programming Language :: Python :: 3
Classifier: License :: OSI Approved :: Apache Software License
Classifier: Operating System :: OS Independent
Requires-Python: >=3.8
License-File: LICENSE
Requires-Dist: httpx
Dynamic: author
Dynamic: author-email
Dynamic: classifier
Dynamic: description
Dynamic: description-content-type
Dynamic: home-page
Dynamic: license-file
Dynamic: requires-dist
Dynamic: requires-python
Dynamic: summary
